Licence.txt
MANIFEST.in
README.md
pyproject.toml
django_reportbroD/admin.py
django_reportbroD/apps.py
django_reportbroD/base.py
django_reportbroD/forms.py
django_reportbroD/menus.py
django_reportbroD/models.py
django_reportbroD/reportcore.py
django_reportbroD/urls.py
django_reportbroD/utils.py
django_reportbroD/views.py
django_reportbroD.egg-info/PKG-INFO
django_reportbroD.egg-info/SOURCES.txt
django_reportbroD.egg-info/dependency_links.txt
django_reportbroD.egg-info/requires.txt
django_reportbroD.egg-info/top_level.txt
django_reportbroD/locale/en/LC_MESSAGES/django.mo
django_reportbroD/locale/en/LC_MESSAGES/django.po
django_reportbroD/locale/es/LC_MESSAGES/django.mo
django_reportbroD/locale/es/LC_MESSAGES/django.po
django_reportbroD/migrations/0001_initial.py
django_reportbroD/migrations/__init__.py
django_reportbroD/static/assets/css/mCSB_buttons.html
django_reportbroD/static/assets/css/owl.video.play.html
django_reportbroD/static/assets/css/style.css
django_reportbroD/static/assets/css/vendors.css
django_reportbroD/static/assets/fonts/cryptocurrency-icons.eot
django_reportbroD/static/assets/fonts/cryptocurrency-icons.html
django_reportbroD/static/assets/fonts/cryptocurrency-icons.svg
django_reportbroD/static/assets/fonts/cryptocurrency-icons.ttf
django_reportbroD/static/assets/fonts/cryptocurrency-icons.woff
django_reportbroD/static/assets/fonts/cryptocurrency-iconsd41d.eot
django_reportbroD/static/assets/fonts/dashicons.eot
django_reportbroD/static/assets/fonts/dashicons.html
django_reportbroD/static/assets/fonts/dashicons.svg
django_reportbroD/static/assets/fonts/dashicons.ttf
django_reportbroD/static/assets/fonts/dashicons.woff
django_reportbroD/static/assets/fonts/dashiconsd41d.eot
django_reportbroD/static/assets/fonts/dripicons.eot
django_reportbroD/static/assets/fonts/dripicons.svg
django_reportbroD/static/assets/fonts/dripicons.ttf
django_reportbroD/static/assets/fonts/dripicons.woff
django_reportbroD/static/assets/fonts/dripiconsd41d.eot
django_reportbroD/static/assets/fonts/feather.eot
django_reportbroD/static/assets/fonts/feather.svg
django_reportbroD/static/assets/fonts/feather.ttf
django_reportbroD/static/assets/fonts/feather.woff
django_reportbrod.egg-info/PKG-INFO
django_reportbrod.egg-info/SOURCES.txt
django_reportbrod.egg-info/dependency_links.txt
django_reportbrod.egg-info/requires.txt
django_reportbrod.egg-info/top_level.txt