Metadata-Version: 2.1
Name: django-reportbroD
Version: 4.1.2
Summary: A Django app to create and use ReportBro reports with a sample admin. This allows you to generate yours reports using three options: by its code or name from database or JSON template.
Author-email: Rider Raúl Espinosa Pérez <riderraule@gmail.com>
Classifier: Environment :: Web Environment
Classifier: Framework :: Django
Classifier: Framework :: Django :: 5.0
Classifier: Intended Audience :: Developers
Classifier: License :: OSI Approved :: BSD License
Classifier: Operating System :: OS Independent
Classifier: Programming Language :: Python
Classifier: Programming Language :: Python :: 3
Classifier: Programming Language :: Python :: 3 :: Only
Classifier: Programming Language :: Python :: 3.10
Classifier: Programming Language :: Python :: 3.11
Classifier: Programming Language :: Python :: 3.12
Classifier: Topic :: Internet :: WWW/HTTP
Classifier: Topic :: Internet :: WWW/HTTP :: Dynamic Content
Requires-Python: >=3.8
License-File: Licence.txt
Requires-Dist: django>=4.2
Requires-Dist: reportbro-lib>=3.7.0
